Workbook

Sheet Instructions
A1: MS Excel Practical Exam
A2: Total Questions: 30
A3: Difficulty Level: Medium
A4: Syllabus: Formulas, Logical Functions, Lookups, INDEX-MATCH, Pivot Tables & Charts, Data Analysis
A5: Attempt all questions using appropriate Excel tools/functions.

Sheet Sheet1

Sheet Sales_Data
A1: Order_ID | B1: Region | C1: Salesperson | D1: Product | E1: Quantity | F1: Unit_Price | G1: Sales_Date | H1: Total Sales | I1: GST | J1: GST AMOUNT | K1: FINAL AMOUNT | L1: GRAND TOTAL | M1: TOTAL ORDERS | N1: MONTH NAME | O1: IF | P1: MAXIMUM | Q1: MINIMUM | R1: LEFT
A2: 301 | B2: North | C2: Amit | D2: Laptop | E2: 2 | F2: 45000 | G2: 05-01-2025 | H2: =E2*F2 -> 90000 | I2: =VLOOKUP(D2,Product_Master!$A$1:$C$4,3,0) -> 0.18 | J2: =I2*H2 -> 16200 | K2: =H2+J2 -> 106200 | L2: =SUM(H8,K8) -> 520200 | M2: =COUNTA(A2:A7) -> 6 | N2: {=TEXT(G2:G7,"MMM")} -> Jan | O2: =IF(E2>3,"High",IF(E2<=3,"Low")) -> Low | P2: =MAX(K2:K7) -> 106200 | Q2: =MIN(K2:K7) -> 53100 | R2: =LEFT(Sales_Data!C2,2) -> Am
A3: 302 | B3: South | C3: Riya | D3: Mobile | E3: 5 | F3: 15000 | G3: 05-01-2026 | H3: =E3*F3 -> 75000 | I3: =VLOOKUP(D3,Product_Master!$A$1:$C$4,3,0) -> 0.12 | J3: =I3*H3 -> 9000 | K3: =H3+J3 -> 84000 | N3: Jan | O3: =IF(E3>3,"High",IF(E3<=3,"Low")) -> High | R3: =LEFT(Sales_Data!C3,2) -> Ri
A4: 303 | B4: East | C4: Kunal | D4: Tablet | E4: 3 | F4: 18000 | G4: 05-01-2027 | H4: =E4*F4 -> 54000 | I4: =VLOOKUP(D4,Product_Master!$A$1:$C$4,3,0) -> 0.12 | J4: =I4*H4 -> 6480 | K4: =H4+J4 -> 60480 | N4: Jan | O4: =IF(E4>3,"High",IF(E4<=3,"Low")) -> Low | R4: =LEFT(Sales_Data!C4,2) -> Ku
A5: 304 | B5: West | C5: Neha | D5: Laptop | E5: 1 | F5: 45000 | G5: 05-01-2028 | H5: =E5*F5 -> 45000 | I5: =VLOOKUP(D5,Product_Master!$A$1:$C$4,3,0) -> 0.18 | J5: =I5*H5 -> 8100 | K5: =H5+J5 -> 53100 | N5: Jan | O5: =IF(E5>3,"High",IF(E5<=3,"Low")) -> Low | R5: =LEFT(Sales_Data!C5,2) -> Ne
A6: 305 | B6: North | C6: Amit | D6: Mobile | E6: 4 | F6: 15000 | G6: 05-01-2029 | H6: =E6*F6 -> 60000 | I6: =VLOOKUP(D6,Product_Master!$A$1:$C$4,3,0) -> 0.12 | J6: =I6*H6 -> 7200 | K6: =H6+J6 -> 67200 | N6: Jan | O6: =IF(E6>3,"High",IF(E6<=3,"Low")) -> High | R6: =LEFT(Sales_Data!C6,2) -> Am
A7: 306 | B7: South | C7: Riya | D7: Laptop | E7: 2 | F7: 45000 | G7: 05-01-2030 | H7: =E7*F7 -> 90000 | I7: =VLOOKUP(D7,Product_Master!$A$1:$C$4,3,0) -> 0.18 | J7: =I7*H7 -> 16200 | K7: =H7+J7 -> 106200 | N7: Jan | O7: =IF(E7>3,"High",IF(E7<=3,"Low")) -> Low | R7: =LEFT(Sales_Data!C7,2) -> Ri
G8: Total | H8: =SUM(H2:H7) -> 414000 | J8: =SUM(J2:J7) -> 63180 | K8: =SUM(K7:K7) -> 106200 | O8: =IF(E8>3,"High",IF(E8<=3,"Low")) -> Low
C11: REGIONWISE SALES | D11: TOTAL
C12: NORTH | D12: =SUMIF($B$2:$B$7,C12,$H$2:$H$7) -> 150000
C13: SOUTH | D13: =SUMIF($B$2:$B$7,C13,$H$2:$H$7) -> 165000
C14: EAST | D14: =SUMIF($B$2:$B$7,C14,$H$2:$H$7) -> 54000
C15: WEST | D15: =SUMIF($B$2:$B$7,C15,$H$2:$H$7) -> 45000

Sheet Product_Master
A1: Product | B1: Category | C1: GST_%
A2: Laptop | B2: Electronics | C2: 0.18
A3: Mobile | B3: Electronics | C3: 0.12
A4: Tablet | B4: Electronics | C4: 0.12

Sheet Student_Marks
A1: Student_ID | B1: Name | C1: Maths | D1: Statistics | E1: Excel | F1: Attendance_% | G1: 14 | H1: concatenate
A2: 1 | B2: Rahul | C2: 78 | D2: 82 | E2: 85 | F2: 92 | G2: =COUNTIF(Student_Marks!F2:F6,">90") -> 3 | H2: =_xlfn.CONCAT(A2:B2) -> 1Rahul
A3: 2 | B3: Sneha | C3: 88 | D3: 91 | E3: 90 | F3: 96 | H3: =_xlfn.CONCAT(A3:B3) -> 2Sneha
A4: 3 | B4: Arjun | C4: 65 | D4: 70 | E4: 72 | F4: 85 | H4: =_xlfn.CONCAT(A4:B4) -> 3Arjun
A5: 4 | B5: Pooja | C5: 92 | D5: 89 | E5: 94 | F5: 98 | H5: =_xlfn.CONCAT(A5:B5) -> 4Pooja
A6: 5 | B6: Vikas | C6: 55 | D6: 60 | E6: 58 | F6: 80 | H6: =_xlfn.CONCAT(A6:B6) -> 5Vikas
A7: TOTAl | C7: =SUM(C2:C6) -> 378 | D7: =SUM(D2:D6) -> 392 | E7: =SUM(E2:E6) -> 399
A8: Average | C8: =AVERAGE(C2:C6) -> 75.6 | D8: =AVERAGE(D2:D6) -> 78.4 | E8: =AVERAGE(E2:E6) -> 79.8
A9: median | D9: =MEDIAN(D2:D6) -> 82
A10: SD
C12: 15 | D12: {=IF(F2:F6>=85,"Eligible","Not Eligible")} -> Eligible
D13: Eligible
D14: Eligible
D15: Eligible
D16: Not Eligible

Sheet Questions
A1: 1. Calculate Total Sales for each order (Quantity × Unit_Price). | J1: 2
A2: 2. Calculate GST Amount using VLOOKUP from Product_Master. | J2: 2
A3: 3. Find Final Amount payable (Total Sales + GST). | J3: 2
A4: 4. Find Grand Total of Final Amount. | J4: 2
A5: 5. Count total number of orders using COUNTA. | J5: 2
A6: 6. Find Region-wise total sales using SUMIF. | J6: 2
A7: 7. Use IF to classify Quantity as High (>3) or Low (<=3). | J7: 2
A8: 8. Find the maximum and minimum Final Amount. | J8: 2
A9: 9. Extract month name from Sales_Date. | J9: 2
A10: 10. Sort Sales_Data by Final Amount (Descending). | J10: 2
A11: 11. Use INDEX-MATCH to fetch Product Category. | J11: 2
A12: 12. Calculate average marks of each student. | J12: 2
... A30: 30. Protect the Student_Marks sheet. | J30: 2
J32: =SUM(J1:J30) -> 60
